Qvis/__init__.py
Qvis/interface.py
Qvis/log_sys.py
Qvis/main.py
Qvis/Config/car.obj
Qvis/Config/color_map.json
Qvis/Config/default.png
Qvis/Config/init_canvas_cfg3d.json
Qvis/Config/layout_config.json
Qvis/Config/menu_bar.json
Qvis/Config/status_bar.json
Qvis/Config/xshow.ico
Qvis/Config/colorful_car/00000.BMP
Qvis/Config/colorful_car/00001.BMP
Qvis/Config/colorful_car/00002.BMP
Qvis/Config/colorful_car/00003.BMP
Qvis/Config/colorful_car/00004.BMP
Qvis/Config/colorful_car/00005.BMP
Qvis/Config/colorful_car/00006.BMP
Qvis/Config/colorful_car/00007.BMP
Qvis/Config/colorful_car/00008.BMP
Qvis/Config/colorful_car/car.obj
Qvis/Config/colorful_car/spot.png
Qvis/Config/colorful_car/uisee.png
Qvis/Controller/__init__.py
Qvis/Controller/controller.py
Qvis/Controller/core.py
Qvis/MagicPipe/__init__.py
Qvis/MagicPipe/pipeline.py
Qvis/Model/__init__.py
Qvis/Model/model.py
Qvis/MsgManager/Exceptions.py
Qvis/MsgManager/README.md
Qvis/MsgManager/UltraDict.py
Qvis/MsgManager/__init__.py
Qvis/MsgManager/manager.py
Qvis/Resources/homepage.png
Qvis/Resources/show_image.jpg
Qvis/Resources/show_pointcloud.png
Qvis/Resources/show_voxel.png
Qvis/SmartParse/smart_parse.py
Qvis/Utils/__init__.py
Qvis/Utils/common_utils.py
Qvis/Utils/navi_state.py
Qvis/Utils/point_cloud_utils.py
Qvis/Utils/pypcd.py
Qvis/View/QxtSpanSlider.py
Qvis/View/box_marker.py
Qvis/View/custom_widget.py
Qvis/View/dock_view.py
Qvis/View/mov_obj.py
Qvis/View/view.py
Qvis/View/viz_core.py
qvis-1.0.2.dist-info/METADATA
qvis-1.0.2.dist-info/WHEEL
qvis-1.0.2.dist-info/entry_points.txt
qvis-1.0.2.dist-info/licenses/LICENSE
qvis-1.0.2.dist-info/RECORD
